ols_client/.DS_Store
ols_client/__init__.py
ols_client/__main__.py
ols_client/cli.py
ols_client/client.py
ols_client/py.typed
ols_client/version.py
ols_client-0.2.1.dist-info/licenses/LICENSE
ols_client-0.2.1.dist-info/WHEEL
ols_client-0.2.1.dist-info/entry_points.txt
ols_client-0.2.1.dist-info/METADATA
ols_client-0.2.1.dist-info/RECORD
